plaintext_analyzer/__init__.py
plaintext_analyzer/entry.py
plaintext_analyzer/file_reader.py
plaintext_analyzer/file_writer.py
plaintext_analyzer/phrase_analyzer.py
plaintext_analyzer/structure_kg_analyzer.py
plaintext_analyzer/vocab_analyzer.py
plaintext_analyzer-0.1.13.dist-info/METADATA
plaintext_analyzer-0.1.13.dist-info/WHEEL
plaintext_analyzer-0.1.13.dist-info/entry_points.txt
plaintext_analyzer-0.1.13.dist-info/RECORD
