Metadata-Version: 2.1
Name: plaintext-analyzer
Version: 0.1.13
Summary: 
Home-page: https://github.com/qishe-nlp/plaintext-analyzer
Keywords: vocabulary,phrases,text,nlp
Author: Phoenix Grey
Author-email: phoenix.grey0108@gmail.com
Requires-Python: >=3.8,<4.0
Classifier: Programming Language :: Python :: 3
Classifier: Programming Language :: Python :: 3.8
Classifier: Programming Language :: Python :: 3.9
Classifier: Programming Language :: Python :: 3.10
Classifier: Programming Language :: Python :: 3.11
Requires-Dist: click (>=8.0.3,<9.0.0)
Requires-Dist: sencore (>=0.1.39,<0.2.0)
Requires-Dist: x2cdict (>=0.1.46,<0.2.0)
Project-URL: Documentation, https://qishe-nlp.github.io/plaintext-analyzer/
Project-URL: Repository, https://github.com/qishe-nlp/plaintext-analyzer
